{
  "data": "31 de Outubro de 2026",
  "versiculo": "O justo viverá da fé.",
  "referencia": "Romanos 1:17",
  "contexto": "(Dia da Reforma Protestante) O versículo que mudou a história através de Martinho Lutero. A base do Evangelho.",
  "significado": "Não vivemos por obras, méritos ou sentimentos. Nossa justiça vem de crer no que Cristo fez. A fé é o ar que o justo respira e o chão onde ele pisa.",
  "mensagem": "Fim de Outubro. Lembre-se: você é aceito por Deus não pelo que faz, mas por quem Jesus é. Essa é a boa notícia! Viva hoje pela fé, sem o peso da religiosidade, desfrutando da graça de Deus."
}