{
  "data": "06 de Março de 2026",
  "versiculo": "Lembra-te do dia do sábado, para o santificar.",
  "referencia": "Êxodo 20:8",
  "contexto": "O quarto mandamento. Deus estabelece um ritmo de trabalho e descanso, imitando a própria Criação.",
  "significado": "Santificar é separar. O descanso não é perda de tempo, é um ato de confiança de que Deus sustenta o mundo mesmo quando paramos. É uma resistência contra a escravidão do ativismo.",
  "mensagem": "Prepare-se para o fim de semana lembrando que você não é uma máquina. O descanso restaura a alma e honra a Deus. Separe um tempo para parar, respirar e reconhecer que é a bênção de Deus, não apenas seu esforço, que traz provisão."
}